wunger_cdk/__init__.py
wunger_cdk/ecr_repo.py
wunger_cdk_constructs/__init__.py
wunger_cdk_constructs/ecr_repo.py
wunger_cdk-0.0.2.dist-info/METADATA
wunger_cdk-0.0.2.dist-info/WHEEL
wunger_cdk-0.0.2.dist-info/top_level.txt
wunger_cdk-0.0.2.dist-info/RECORD
