Metadata-Version: 2.1
Name: wunger-cdk
Version: 0.0.2
Summary: CDK python package
Home-page: https://upload.pypi.org/legacy/
Author: Wolfgang Unger
Author-email: wolfgang.unger@sccbrasil.com
License: UNKNOWN
Platform: UNKNOWN
Classifier: Programming Language :: Python :: 3
Classifier: License :: OSI Approved :: MIT License
Classifier: Operating System :: OS Independent
